revpref/__init__.py
revpref/_jit.py
revpref/_legacy.py
revpref/_utils.py
revpref/avi.py
revpref/ccei.py
revpref/garp.py
revpref/hmi.py
revpref/mci.py
revpref/me.py
revpref/mpi.py
revpref-1.0.5.dist-info/METADATA
revpref-1.0.5.dist-info/WHEEL
revpref-1.0.5.dist-info/top_level.txt
revpref-1.0.5.dist-info/RECORD
