Metadata-Version: 2.1
Name: revpref
Version: 1.0.5
Summary: Python Tools for Computational Revealed Preference Analysis
Home-page: https://github.com/Aliebc/revpref
Author: Yi Xiang
Author-email: Yi Xiang <xiangy.i@outlook.com>
Project-URL: Homepage, https://github.com/Aliebc/revpref
Project-URL: Bug Tracker, https://github.com/Aliebc/revpref
Classifier: Programming Language :: Python :: 3
Requires-Python: >=3.10
Requires-Dist: numpy
Requires-Dist: networkx
Requires-Dist: pulp >=2.6.0
Requires-Dist: scipy >1.10
Requires-Dist: matplotlib
